s3sqlite.py
s3sqlite-0.2.1.dist-info/LICENSE
s3sqlite-0.2.1.dist-info/METADATA
s3sqlite-0.2.1.dist-info/WHEEL
s3sqlite-0.2.1.dist-info/top_level.txt
s3sqlite-0.2.1.dist-info/RECORD
