Metadata-Version: 2.1
Name: s3sqlite
Version: 0.2.1
Summary: Query SQLite databases on S3 using s3fs
Home-page: https://github.com/litements/s3sqlite
Author: Ricardo Ander-Egg Aguilar
Author-email: rsubacc@gmail.com
Classifier: Operating System :: OS Independent
Requires-Python: >=3.7
License-File: LICENSE
Requires-Dist: fsspec
Requires-Dist: apsw
Requires-Dist: s3fs
Requires-Dist: boto3
